altered_deckfmt/__init__.py
altered_deckfmt/decoder.py
altered_deckfmt/encoder.py
altered_deckfmt/exceptions.py
altered_deckfmt/logging_config.py
altered_deckfmt/models.py
altered_deckfmt/utils.py
altered_deckfmt-0.1.1.dist-info/LICENSE
altered_deckfmt-0.1.1.dist-info/METADATA
altered_deckfmt-0.1.1.dist-info/WHEEL
altered_deckfmt-0.1.1.dist-info/top_level.txt
altered_deckfmt-0.1.1.dist-info/RECORD
