Metadata-Version: 2.1
Name: altered_deckfmt
Version: 0.1.1
Summary: A compact format to share decklists for Altered TCG
Author: Ajordat, Taum
Maintainer: Ajordat
License: MIT License
Project-URL: Repository, https://github.com/Ajordat/altered_deckfmt
Project-URL: Issues, https://github.com/Ajordat/altered_deckfmt/issues
Project-URL: Parent, https://github.com/Taum/altered-deckfmt
Classifier: Programming Language :: Python :: 3
Classifier: License :: OSI Approved :: MIT License
Classifier: Operating System :: OS Independent
Requires-Python: >=3.12
License-File: LICENSE
